{
  "type": "minecraft:chest",
  "pools": [
    {
      "rolls": {
        "type": "minecraft:uniform",
        "min": 2.0,
        "max": 8.0
      },
      "bonus_rolls": 0.0,
      "entries": [
        {
          "type": "minecraft:item",
          "weight": 10,
          "functions": [
            {
              "function": "minecraft:set_count",
              "count": {
                "type": "minecraft:uniform",
                "min": 1.0,
                "max": 4.0
              },
              "add": false
            }
          ],
          "name": "minecraft:coal"
        },
        {
          "type": "minecraft:item",
          "weight": 10,
          "functions": [
            {
              "function": "minecraft:set_count",
              "count": {
                "type": "minecraft:uniform",
                "min": 1.0,
                "max": 3.0
              },
              "add": false
            }
          ],
          "name": "minecraft:gold_nugget"
        },
        {
          "type": "minecraft:item",
          "name": "minecraft:emerald"
        },
        {
          "type": "minecraft:item",
          "weight": 10,
          "functions": [
            {
              "function": "minecraft:set_count",
              "count": {
                "type": "minecraft:uniform",
                "min": 2.0,
                "max": 3.0
              },
              "add": false
            }
          ],
          "name": "minecraft:wheat"
        }
      ]
    },
    {
      "rolls": 1.0,
      "bonus_rolls": 0.0,
      "entries": [
        {
          "type": "minecraft:item",
          "name": "minecraft:golden_apple"
        },
        {
          "type": "minecraft:item",
          "weight": 5,
          "functions": [
            {
              "function": "minecraft:enchant_randomly"
            }
          ],
          "name": "minecraft:book"
        },
        {
          "type": "minecraft:item",
          "name": "minecraft:leather_chestplate"
        },
        {
          "type": "minecraft:item",
          "name": "minecraft:golden_helmet"
        },
        {
          "type": "minecraft:item",
          "weight": 5,
          "functions": [
            {
              "function": "minecraft:enchant_randomly"
            }
          ],
          "name": "minecraft:fishing_rod"
        },
        {
          "type": "minecraft:item",
          "weight": 10,
          "functions": [
            {
              "function": "minecraft:exploration_map",
              "decoration": "red_x",
              "zoom": 1,
              "skip_existing_chunks": false
            }
          ],
          "name": "minecraft:map"
        }
      ]
    },
	    {
      "rolls": 2.0,
      "bonus_rolls": 0.0,
      "entries": [
				{
					"type": "item",
					"name": "minecraft:player_head",
					"functions": [
						{
							"function": "set_nbt",
							"tag": "{display:{Name:\"{\\\"text\\\":\\\"Crate\\\"}\"},SkullOwner:{Id:[I;2075206903,1102203097,-2107118560,2027789071],Properties:{textures:[{Value:\"eyJ0ZXh0dXJlcyI6eyJTS0lOIjp7InVybCI6Imh0dHA6Ly90ZXh0dXJlcy5taW5lY3JhZnQubmV0L3RleHR1cmUvYTJkZDdkODE4Y2JhNjUyYjAxY2YzNTBkMmIyYTFjZWVkZDRmNDZhY2FkMDViMmNlODFjM2Y4NzdlYWI3MTcifX19\"}]}}}"
						}
					],
					"weight": 10
				},
								{
					"type": "item",
					"name": "minecraft:potion",
					"weight": 2,
					"functions": [
						{
							"function": "set_nbt",
							"tag": "{CustomPotionEffects:[{Id:14,Duration:1800,ShowParticles:0b}],CustomPotionColor:11727605,display:{Name:\"{\\\"text\\\":\\\"Potion of True Invisibility\\\"}\",Lore:[\"A more powerful version\",\"of Invisibility, its\",\"recipe lost to time.\"]}}"
						}
					]
				},
											{
					"type": "item",
					"name": "minecraft:iron_axe",
					"weight": 2,
					"functions": [
						{
							"function": "set_nbt",
							"tag": "{display:{Name:\"{\\\"text\\\":\\\"Arbor Druid Axe\\\"}\", Lore:[\"Increased chance of saplings\", \"from leaf blocks\"]}, Enchantments:[{id:\"fortune\", lvl:7s}], RepairCost:99}"
						}
					]
				},
															{
					"type": "item",
					"name": "minecraft:player_head",
					"functions": [
						{
							"function": "set_nbt",
							"tag": "{display:{Name:\"{\\\"text\\\":\\\"Candle (red)\\\"}\"},SkullOwner:{Id:[I;1160891075,268519242,-1488969557,505795998],Properties:{textures:[{Value:\"eyJ0ZXh0dXJlcyI6eyJTS0lOIjp7InVybCI6Imh0dHA6Ly90ZXh0dXJlcy5taW5lY3JhZnQubmV0L3RleHR1cmUvYTEzODgyNDhhYzFhOTA1YWNmZWM4MDE3MjkyOTNjZTVlYmE3OGViODlhNzAzYTJiOWQ4N2MxZTVhYzExMDQ3NCJ9fX0=\"}]}}}"
						}
					],
					"weight": 10
				},
				{
					"type": "item",
					"name": "minecraft:red_banner",
					"weight": 10,
					"functions": [
						{
							"function": "set_nbt",
							"tag": "{display:{Name:\"{\\\"text\\\":\\\"Cake\\\"}\", Lore:[\"By Tetrajak\"]}, BlockEntityTag:{Patterns:[{Pattern:ss,Color:0},{Pattern:bri,Color:0},{Pattern:hhb,Color:12},{Pattern:ts,Color:15},{Pattern:bs,Color:15},{Pattern:bo,Color:15}]}}"
						}
					]
				},
				{
					"type": "item",
					"name": "minecraft:purple_banner",
					"weight": 10,
					"functions": [
						{
							"function": "set_nbt",
							"tag": "{display:{Name:\"{\\\"text\\\":\\\"Boiling Cauldron\\\"}\", Lore:[\"By Tetrajak\"]}, BlockEntityTag:{Patterns:[{Pattern:bri,Color:8},{Pattern:tl,Color:10},{Pattern:tt,Color:10},{Pattern:sku,Color:10},{Pattern:bs,Color:15},{Pattern:cbo,Color:10},{Pattern:bts,Color:15},{Pattern:bo,Color:10}]}}"
						}
					]
				}
      ]
    }
  ]
}
