{
	"format_version": "1.8.0",
	"animations": {
		"idle": {
			"loop": true,
			"animation_length": 0.52,
			"bones": {
				"birdman": {
					"rotation": [42.5, 0, 0],
					"position": {
						"0.0": [0, 0, 0],
						"0.2": [0, -2.57, 0],
						"0.36": [0, -3, 0],
						"0.52": [0, 0, 0]
					}
				},
				"leftleg": {
					"rotation": {
						"0.0": [65, 32.5, 0],
						"0.28": [95, 32.5, 0],
						"0.52": [65, 32.5, 0]
					}
				},
				"leftwing": {
					"rotation": {
						"0.0": [0, 47.5, 22.5],
						"0.2": [-30, 2.5, -40],
						"0.36": [-15, 65, 48.75],
						"0.52": [0, 47.5, 22.5]
					}
				},
				"head": {
					"rotation": [-30, 0, 0]
				},
				"rightwing": {
					"rotation": {
						"0.0": [-37.5, -37.5, 0],
						"0.2": [-50, 2.5, 57.5],
						"0.36": [-43.75, -65, -16.25],
						"0.52": [-37.5, -37.5, 0]
					}
				},
				"rightleg": {
					"rotation": {
						"0.0": [45, -17.5, 0],
						"0.28": [87.5, -17.5, 0],
						"0.52": [45, -17.5, 0]
					}
				}
			}
		},
		"swarm": {
			"animation_length": 2.6,
			"override_previous_animation": true,
			"bones": {
				"birdman": {
					"rotation": {
						"0.0": [100, 55, 35],
						"0.28": [42.5, 5, 0],
						"0.52": [42.5, -107.5, 42.5],
						"0.8": [15, -185, 0],
						"1.04": [42.5, -265, 0],
						"1.32": [42.5, -360, 62.5],
						"1.56": [2.5, -457.5, 0],
						"1.84": [77.5, -540, 0],
						"2.08": [42.5, -632.5, 0],
						"2.36": [10, -722.5, 0],
						"2.6": [42.5, -820, 0]
					},
					"position": {
						"0.0": [0, 0, 19],
						"0.28": [-16, 0, 1],
						"0.52": [0, -9, -15],
						"0.8": [16, 0, -2],
						"1.04": [-2, 7, 14],
						"1.32": [-20, -5, 2],
						"1.56": [-2, 0, -16],
						"1.84": [15, 0, -2],
						"2.08": [-3, -11, 16],
						"2.36": [-19, 0, 0],
						"2.6": [-2, 0, -17]
					}
				},
				"leftleg": {
					"rotation": {
						"0.0": [65, 32.5, 0],
						"0.28": [95, 32.5, 0],
						"0.52": [65, 32.5, 0],
						"0.8": [95, 32.5, 0],
						"1.04": [65, 32.5, 0],
						"1.32": [95, 32.5, 0],
						"1.56": [65, 32.5, 0],
						"1.84": [95, 32.5, 0],
						"2.08": [65, 32.5, 0],
						"2.36": [95, 32.5, 0],
						"2.6": [65, 32.5, 0]
					}
				},
				"leftwing": {
					"rotation": {
						"0.0": [0, 47.5, 22.5],
						"0.2": [-30, 2.5, -40],
						"0.36": [-15, 65, 48.75],
						"0.52": [0, 47.5, 22.5],
						"0.72": [-30, 2.5, -40],
						"0.88": [-15, 65, 48.75],
						"1.04": [0, 47.5, 22.5],
						"1.24": [-30, 2.5, -40],
						"1.4": [-15, 65, 48.75],
						"1.56": [0, 47.5, 22.5],
						"1.76": [-30, 2.5, -40],
						"1.92": [-15, 65, 48.75],
						"2.08": [0, 47.5, 22.5],
						"2.28": [-30, 2.5, -40],
						"2.44": [-15, 65, 48.75],
						"2.6": [0, 47.5, 22.5]
					}
				},
				"head": {
					"rotation": [-30, 0, 0]
				},
				"rightwing": {
					"rotation": {
						"0.0": [-37.5, -37.5, 0],
						"0.2": [-50, 2.5, 57.5],
						"0.36": [-43.75, -65, -16.25],
						"0.52": [-37.5, -37.5, 0],
						"0.72": [-50, 2.5, 57.5],
						"0.88": [-43.75, -65, -16.25],
						"1.04": [-37.5, -37.5, 0],
						"1.24": [-50, 2.5, 57.5],
						"1.4": [-43.75, -65, -16.25],
						"1.56": [-37.5, -37.5, 0],
						"1.76": [-50, 2.5, 57.5],
						"1.92": [-43.75, -65, -16.25],
						"2.08": [-37.5, -37.5, 0],
						"2.28": [-50, 2.5, 57.5],
						"2.44": [-43.75, -65, -16.25],
						"2.6": [-37.5, -37.5, 0]
					}
				},
				"rightleg": {
					"rotation": {
						"0.0": [45, -17.5, 0],
						"0.28": [87.5, -17.5, 0],
						"0.52": [45, -17.5, 0],
						"0.8": [87.5, -17.5, 0],
						"1.04": [45, -17.5, 0],
						"1.32": [87.5, -17.5, 0],
						"1.56": [45, -17.5, 0],
						"1.84": [87.5, -17.5, 0],
						"2.08": [45, -17.5, 0],
						"2.36": [87.5, -17.5, 0],
						"2.6": [45, -17.5, 0]
					}
				}
			}
		}
	}
}